{
	"info": {
		"_postman_id": "6d1973cd-b00a-4744-b1b5-a8fa5efb656d",
		"name": "Project Perpustakaan Global Institute",
		"schema": "https://schema.getpostman.com/json/collection/v2.1.0/collection.json",
		"_exporter_id": "30170047"
	},
	"item": [
		{
			"name": "Buku",
			"item": [
				{
					"name": "POST Create Buku",
					"request": {
						"auth": {
							"type": "bearer",
							"bearer": [
								{
									"key": "token",
									"value": "eyJhbGciOiJIUzI1NiIsInR5cCI6IkpXVCJ9.eyJpZCI6MSwiVXNlcm5hbWUiOiJNb2hhbW1hZFJhZGphMjgiLCJpc0FkbWluIjp0cnVlLCJpYXQiOjE3MDA1NDUyNTN9.meHqrIKt-BOlbVT-6vvm0Z1L5EeMInmJ1xJ4jAvD7-Q",
									"type": "string"
								}
							]
						},
						"method": "POST",
						"header": [],
						"body": {
							"mode": "raw",
							"raw": "{\n      \"JudulBuku\": \"Rekayasa Perangkat Lunak\",\n      \"Pengarang\": \"Mohammad Radja\",\n      \"Kategori\": \"Buku Pengetahuan Teknologi\",\n      \"Penerbit\": \"PT Gramedia Media Pustaka\",\n      \"Tahun\": \"2021-01-01\"\n}",
							"options": {
								"raw": {
									"language": "json"
								}
							}
						},
						"url": {
							"raw": "http://localhost:3000/buku",
							"protocol": "http",
							"host": [
								"localhost"
							],
							"port": "3000",
							"path": [
								"buku"
							]
						}
					},
					"response": []
				},
				{
					"name": "GET List Buku",
					"request": {
						"method": "GET",
						"header": [],
						"url": {
							"raw": "http://localhost:3000/buku",
							"protocol": "http",
							"host": [
								"localhost"
							],
							"port": "3000",
							"path": [
								"buku"
							]
						}
					},
					"response": []
				},
				{
					"name": "GET Buku By ID",
					"request": {
						"method": "GET",
						"header": [],
						"url": {
							"raw": "http://localhost:3000/buku/:id",
							"protocol": "http",
							"host": [
								"localhost"
							],
							"port": "3000",
							"path": [
								"buku",
								":id"
							],
							"variable": [
								{
									"key": "id",
									"value": "1"
								}
							]
						}
					},
					"response": []
				},
				{
					"name": "PUT Buku Update Data",
					"request": {
						"auth": {
							"type": "bearer",
							"bearer": [
								{
									"key": "token",
									"value": "eyJhbGciOiJIUzI1NiIsInR5cCI6IkpXVCJ9.eyJpZCI6MSwiZW1haWwiOiJ2b2Nhc2lhQGVtYWlsLmNvbSIsImlhdCI6MTY5NzUyODM2M30.ciOlPjuhBoNGRmad98VOAYK4eUnwTPryphF9bfGd7-4",
									"type": "string"
								}
							]
						},
						"method": "PUT",
						"header": [],
						"body": {
							"mode": "raw",
							"raw": "{\n  \"JudulBuku\": \"\",\n  \"Pengarang\": \"\",\n  \"Kategori\": \"\",\n  \"Penerbit\": \"\",\n  \"Tahun\": \n}",
							"options": {
								"raw": {
									"language": "json"
								}
							}
						},
						"url": {
							"raw": "http://localhost:3000/buku/:id",
							"protocol": "http",
							"host": [
								"localhost"
							],
							"port": "3000",
							"path": [
								"buku",
								":id"
							],
							"variable": [
								{
									"key": "id",
									"value": ""
								}
							]
						}
					},
					"response": []
				},
				{
					"name": "DELETE Buku by ID",
					"request": {
						"auth": {
							"type": "bearer",
							"bearer": [
								{
									"key": "token",
									"value": "eyJhbGciOiJIUzI1NiIsInR5cCI6IkpXVCJ9.eyJpZCI6MSwiZW1haWwiOiJ2b2Nhc2lhQGVtYWlsLmNvbSIsImlhdCI6MTY5NzUyODM2M30.ciOlPjuhBoNGRmad98VOAYK4eUnwTPryphF9bfGd7-4",
									"type": "string"
								}
							]
						},
						"method": "DELETE",
						"header": [],
						"url": {
							"raw": "http://localhost:3000/movie/:id",
							"protocol": "http",
							"host": [
								"localhost"
							],
							"port": "3000",
							"path": [
								"movie",
								":id"
							],
							"variable": [
								{
									"key": "id",
									"value": "1"
								}
							]
						}
					},
					"response": []
				}
			]
		},
		{
			"name": "Peminjaman",
			"item": [
				{
					"name": "POST Create Peminjaman",
					"request": {
						"auth": {
							"type": "bearer",
							"bearer": [
								{
									"key": "token",
									"value": "eyJhbGciOiJIUzI1NiIsInR5cCI6IkpXVCJ9.eyJpZCI6NywiZW1haWwiOiJSYWRqYTEyM0BnbWFpbC5jb20iLCJpc0FkbWluIjp0cnVlLCJpYXQiOjE2OTgwMDQ5Njd9.tOGp557WrVfPp0rrDxpwLBrGFn0zJlYO0wc78VuNtj8",
									"type": "string"
								}
							]
						},
						"method": "POST",
						"header": [
							{
								"key": "id",
								"value": "",
								"type": "text",
								"disabled": true
							}
						],
						"body": {
							"mode": "raw",
							"raw": "{\n   \"JudulBuku\": \"Rekayasa Perangkat Lunak\",\n   \"TanggalPinjam\": \"2023-09-28\",\n   \"TanggalKembali\": \"2023-12-28\",\n   \"Denda\": \"50000\",\n   \"IDBuku\": 111,\n   \"IDAnggota\": 121\n}",
							"options": {
								"raw": {
									"language": "json"
								}
							}
						},
						"url": {
							"raw": "http://localhost:3000/peminjaman",
							"protocol": "http",
							"host": [
								"localhost"
							],
							"port": "3000",
							"path": [
								"peminjaman"
							]
						}
					},
					"response": []
				},
				{
					"name": "GET List Peminjaman",
					"request": {
						"method": "GET",
						"header": [],
						"url": {
							"raw": "http://localhost:3000/peminjaman",
							"protocol": "http",
							"host": [
								"localhost"
							],
							"port": "3000",
							"path": [
								"peminjaman"
							]
						}
					},
					"response": []
				},
				{
					"name": "PUT Peminjaman Update Data",
					"request": {
						"auth": {
							"type": "bearer",
							"bearer": [
								{
									"key": "token",
									"value": "eyJhbGciOiJIUzI1NiIsInR5cCI6IkpXVCJ9.eyJpZCI6MSwiZW1haWwiOiJ2b2Nhc2lhQGVtYWlsLmNvbSIsImlhdCI6MTY5NzUyODM2M30.ciOlPjuhBoNGRmad98VOAYK4eUnwTPryphF9bfGd7-4",
									"type": "string"
								}
							]
						},
						"method": "PUT",
						"header": [],
						"body": {
							"mode": "raw",
							"raw": "{\n  \"IDPeminjaman\": \"\",\n   \"JudulBuku\": \"\",\n   \"TanggalPinjam\": ,\n   \"TanggalKembali\": ,\n   \"Denda\": ,\n   \"IDBuku\": ,\n   \"IDAnggota\": \n}",
							"options": {
								"raw": {
									"language": "json"
								}
							}
						},
						"url": {
							"raw": "http://localhost:3000/peminjaman/:id",
							"protocol": "http",
							"host": [
								"localhost"
							],
							"port": "3000",
							"path": [
								"peminjaman",
								":id"
							],
							"variable": [
								{
									"key": "id",
									"value": ""
								}
							]
						}
					},
					"response": []
				},
				{
					"name": "DELETE Peminjaman by ID",
					"request": {
						"auth": {
							"type": "bearer",
							"bearer": [
								{
									"key": "token",
									"value": "eyJhbGciOiJIUzI1NiIsInR5cCI6IkpXVCJ9.eyJpZCI6MSwiZW1haWwiOiJ2b2Nhc2lhQGVtYWlsLmNvbSIsImlhdCI6MTY5NzUyODM2M30.ciOlPjuhBoNGRmad98VOAYK4eUnwTPryphF9bfGd7-4",
									"type": "string"
								}
							]
						},
						"method": "DELETE",
						"header": [],
						"url": {
							"raw": "http://localhost:3000/peminjaman/:id",
							"protocol": "http",
							"host": [
								"localhost"
							],
							"port": "3000",
							"path": [
								"peminjaman",
								":id"
							],
							"variable": [
								{
									"key": "id",
									"value": "1"
								}
							]
						}
					},
					"response": []
				}
			]
		},
		{
			"name": "Anggota",
			"item": [
				{
					"name": "POST Create Anggota",
					"request": {
						"auth": {
							"type": "bearer",
							"bearer": [
								{
									"key": "token",
									"value": "eyJhbGciOiJIUzI1NiIsInR5cCI6IkpXVCJ9.eyJpZCI6NywiZW1haWwiOiJSYWRqYTEyM0BnbWFpbC5jb20iLCJpc0FkbWluIjp0cnVlLCJpYXQiOjE2OTgwMDQ5Njd9.tOGp557WrVfPp0rrDxpwLBrGFn0zJlYO0wc78VuNtj8",
									"type": "string"
								}
							]
						},
						"method": "POST",
						"header": [
							{
								"key": "id",
								"value": "",
								"type": "text",
								"disabled": true
							}
						],
						"body": {
							"mode": "raw",
							"raw": "{\n        \"Nama\": \"Risma Ayu\",\n        \"Jurusan\": \"Teknik Informatika\",\n        \"MasaBerlaku\": \"2024-01-01\"\n}",
							"options": {
								"raw": {
									"language": "json"
								}
							}
						},
						"url": {
							"raw": "http://localhost:3000/anggota",
							"protocol": "http",
							"host": [
								"localhost"
							],
							"port": "3000",
							"path": [
								"anggota"
							]
						}
					},
					"response": []
				},
				{
					"name": "GET List Anggota",
					"request": {
						"method": "GET",
						"header": [],
						"url": {
							"raw": "http://localhost:3000/anggota",
							"protocol": "http",
							"host": [
								"localhost"
							],
							"port": "3000",
							"path": [
								"anggota"
							]
						}
					},
					"response": []
				},
				{
					"name": "PUT Anggota Update Data",
					"request": {
						"auth": {
							"type": "bearer",
							"bearer": [
								{
									"key": "token",
									"value": "eyJhbGciOiJIUzI1NiIsInR5cCI6IkpXVCJ9.eyJpZCI6MSwiZW1haWwiOiJ2b2Nhc2lhQGVtYWlsLmNvbSIsImlhdCI6MTY5NzUyODM2M30.ciOlPjuhBoNGRmad98VOAYK4eUnwTPryphF9bfGd7-4",
									"type": "string"
								}
							]
						},
						"method": "PUT",
						"header": [],
						"body": {
							"mode": "raw",
							"raw": "{\n  \"IDAnggota\": ,\n   \"Nama\": ,\n   \"Jurusan\": ,\n   \"MasaBerlaku\": \n}",
							"options": {
								"raw": {
									"language": "json"
								}
							}
						},
						"url": {
							"raw": "http://localhost:3000/anggota/:id",
							"protocol": "http",
							"host": [
								"localhost"
							],
							"port": "3000",
							"path": [
								"anggota",
								":id"
							],
							"variable": [
								{
									"key": "id",
									"value": ""
								}
							]
						}
					},
					"response": []
				},
				{
					"name": "DELETE Anggota by ID",
					"request": {
						"auth": {
							"type": "bearer",
							"bearer": [
								{
									"key": "token",
									"value": "eyJhbGciOiJIUzI1NiIsInR5cCI6IkpXVCJ9.eyJpZCI6MSwiZW1haWwiOiJ2b2Nhc2lhQGVtYWlsLmNvbSIsImlhdCI6MTY5NzUyODM2M30.ciOlPjuhBoNGRmad98VOAYK4eUnwTPryphF9bfGd7-4",
									"type": "string"
								}
							]
						},
						"method": "DELETE",
						"header": [],
						"url": {
							"raw": "http://localhost:3000/anggota/:id",
							"protocol": "http",
							"host": [
								"localhost"
							],
							"port": "3000",
							"path": [
								"anggota",
								":id"
							],
							"variable": [
								{
									"key": "id",
									"value": "1"
								}
							]
						}
					},
					"response": []
				}
			]
		},
		{
			"name": "Petugas",
			"item": [
				{
					"name": "Register",
					"request": {
						"auth": {
							"type": "bearer"
						},
						"method": "POST",
						"header": [],
						"body": {
							"mode": "raw",
							"raw": "{\n        \"Nama\": \"Radja\",\n        \"Username\": \"MohammadRadja28\",\n        \"Password\": \"Radja12345\"\n}\n  ",
							"options": {
								"raw": {
									"language": "json"
								}
							}
						},
						"url": {
							"raw": "http://localhost:3000/register",
							"protocol": "http",
							"host": [
								"localhost"
							],
							"port": "3000",
							"path": [
								"register"
							]
						}
					},
					"response": []
				},
				{
					"name": "Login",
					"request": {
						"auth": {
							"type": "noauth"
						},
						"method": "POST",
						"header": [],
						"body": {
							"mode": "raw",
							"raw": "{\n        \"Nama\": \"Radja\",\n        \"Username\": \"MohammadRadja28\",\n        \"Password\": \"Radja12345\"\n}\n",
							"options": {
								"raw": {
									"language": "json"
								}
							}
						},
						"url": {
							"raw": "http://localhost:3000/login",
							"protocol": "http",
							"host": [
								"localhost"
							],
							"port": "3000",
							"path": [
								"login"
							]
						}
					},
					"response": []
				}
			]
		}
	]
}